nixnet/__init__.py
nixnet/_cconsts.py
nixnet/_cfuncs.py
nixnet/_cprops.py
nixnet/_ctypedefs.py
nixnet/_enums.py
nixnet/_errors.py
nixnet/_frames.py
nixnet/_funcs.py
nixnet/_lib.py
nixnet/_props.py
nixnet/_session/__init__.py
nixnet/_session/base.py
nixnet/_session/collection.py
nixnet/_session/frames.py
nixnet/_session/intf.py
nixnet/_session/j1939.py
nixnet/_session/signals.py
nixnet/_utils.py
nixnet/constants.py
nixnet/convert.py
nixnet/database/__init__.py
nixnet/database/_cluster.py
nixnet/database/_collection.py
nixnet/database/_database_object.py
nixnet/database/_dbc_attributes.py
nixnet/database/_dbc_signal_value_table.py
nixnet/database/_ecu.py
nixnet/database/_find_object.py
nixnet/database/_frame.py
nixnet/database/_lin_sched.py
nixnet/database/_lin_sched_entry.py
nixnet/database/_pdu.py
nixnet/database/_signal.py
nixnet/database/_subframe.py
nixnet/database/database.py
nixnet/errors.py
nixnet/session.py
nixnet/system/__init__.py
nixnet/system/_collection.py
nixnet/system/_databases.py
nixnet/system/_device.py
nixnet/system/_interface.py
nixnet/system/system.py
nixnet/types.py
nixnet-1.0.0.dist-info/LICENSE
nixnet-1.0.0.dist-info/METADATA
nixnet-1.0.0.dist-info/WHEEL
nixnet-1.0.0.dist-info/RECORD
