Metadata-Version: 2.1
Name: nixnet
Version: 1.0.0
Summary: NI-XNET Python API
Home-page: https://github.com/ni/nixnet-python
License: MIT
Keywords: nixnet
Author: NI
Author-email: opensource@ni.com
Requires-Python: >=3.9,<4.0
Classifier: Development Status :: 5 - Production/Stable
Classifier: Intended Audience :: Developers
Classifier: Intended Audience :: Manufacturing
Classifier: Intended Audience :: Science/Research
Classifier: License :: OSI Approved :: MIT License
Classifier: Operating System :: Microsoft :: Windows
Classifier: Operating System :: POSIX
Classifier: Programming Language :: Python :: 3
Classifier: Programming Language :: Python :: 3.9
Classifier: Programming Language :: Python :: 3.10
Classifier: Programming Language :: Python :: 3.11
Classifier: Programming Language :: Python :: 3.12
Classifier: Programming Language :: Python :: 3.13
Classifier: Programming Language :: Python :: Implementation :: CPython
Classifier: Programming Language :: Python :: Implementation :: PyPy
Classifier: Topic :: System :: Hardware :: Hardware Drivers
Requires-Dist: six
Project-URL: Documentation, https://nixnet.readthedocs.io
Project-URL: Repository, https://github.com/ni/nixnet-python
